qlib/__init__.py
qlib/config.py
qlib/constant.py
qlib/log.py
qlib/typehint.py
qlib/backtest/__init__.py
qlib/backtest/account.py
qlib/backtest/backtest.py
qlib/backtest/decision.py
qlib/backtest/exchange.py
qlib/backtest/executor.py
qlib/backtest/high_performance_ds.py
qlib/backtest/position.py
qlib/backtest/profit_attribution.py
qlib/backtest/report.py
qlib/backtest/signal.py
qlib/backtest/utils.py
qlib/contrib/__init__.py
qlib/contrib/evaluate.py
qlib/contrib/evaluate_portfolio.py
qlib/contrib/torch.py
qlib/contrib/data/__init__.py
qlib/contrib/data/data.py
qlib/contrib/data/dataset.py
qlib/contrib/data/handler.py
qlib/contrib/data/highfreq_handler.py
qlib/contrib/data/highfreq_processor.py
qlib/contrib/data/highfreq_provider.py
qlib/contrib/data/loader.py
qlib/contrib/data/processor.py
qlib/contrib/data/utils/__init__.py
qlib/contrib/data/utils/sepdf.py
qlib/contrib/eva/__init__.py
qlib/contrib/eva/alpha.py
qlib/contrib/meta/__init__.py
qlib/contrib/meta/data_selection/__init__.py
qlib/contrib/meta/data_selection/dataset.py
qlib/contrib/meta/data_selection/model.py
qlib/contrib/meta/data_selection/net.py
qlib/contrib/meta/data_selection/utils.py
qlib/contrib/model/__init__.py
qlib/contrib/model/catboost_model.py
qlib/contrib/model/double_ensemble.py
qlib/contrib/model/gbdt.py
qlib/contrib/model/highfreq_gdbt_model.py
qlib/contrib/model/linear.py
qlib/contrib/model/pytorch_adarnn.py
qlib/contrib/model/pytorch_add.py
qlib/contrib/model/pytorch_alstm.py
qlib/contrib/model/pytorch_alstm_ts.py
qlib/contrib/model/pytorch_gats.py
qlib/contrib/model/pytorch_gats_ts.py
qlib/contrib/model/pytorch_general_nn.py
qlib/contrib/model/pytorch_gru.py
qlib/contrib/model/pytorch_gru_ts.py
qlib/contrib/model/pytorch_hist.py
qlib/contrib/model/pytorch_igmtf.py
qlib/contrib/model/pytorch_krnn.py
qlib/contrib/model/pytorch_localformer.py
qlib/contrib/model/pytorch_localformer_ts.py
qlib/contrib/model/pytorch_lstm.py
qlib/contrib/model/pytorch_lstm_ts.py
pyqlib_auto-0.0.1.dist-info/LICENSE
pyqlib_auto-0.0.1.dist-info/METADATA
pyqlib_auto-0.0.1.dist-info/WHEEL
pyqlib_auto-0.0.1.dist-info/entry_points.txt
pyqlib_auto-0.0.1.dist-info/top_level.txt
pyqlib_auto-0.0.1.dist-info/RECORD
